{
	"id":20768,
	"Skill_ID":2214,
	"Skill_Lv":3,
	"skillEffect":"1153.0",
	"Skill_Type":4,
	"name":"淬体",
	"qingjiaotype":7,
	"seid":[
		31,
		5
	],
	"Affix":[],
	"Affix2":[],
	"descr":"回合结束时，吸收先天灵气提升淬体进度，本次淬体只能使用一次。",
	"TuJiandescr":"回合结束时，吸收先天灵气提升淬体进度，本次淬体只能使用一次。",
	"AttackType":[
		20
	],
	"script":"SkillSelf",
	"HP":0,
	"speed":0,
	"icon":0,
	"Skill_DisplayType":0,
	"skill_SameCastNum":[
		2,
		2
	],
	"skill_CastType":[],
	"skill_Cast":[],
	"Skill_LV":3,
	"typePinJie":1,
	"DF":0,
	"TuJianType":0,
	"Skill_Open":0,
	"Skill_castTime":1,
	"canUseDistMax":30,
	"CD":10000
}